pyrethrin/__init__.py
pyrethrin/__main__.py
pyrethrin/_ast_dump.py
pyrethrin/async_support.py
pyrethrin/decorators.py
pyrethrin/exceptions.py
pyrethrin/match.py
pyrethrin/option.py
pyrethrin/py.typed
pyrethrin/result.py
pyrethrin/testing.py
pyrethrin/bin/.gitkeep
pyrethrin/bin/pyrethrum-darwin-arm64
pyrethrin/bin/pyrethrum-darwin-x64
pyrethrin/shields/fastapi/__init__.py
pyrethrin/shields/numpy/__init__.py
pyrethrin/shields/pandas/__init__.py
pyrethrin-0.2.0.dist-info/METADATA
pyrethrin-0.2.0.dist-info/WHEEL
pyrethrin-0.2.0.dist-info/entry_points.txt
pyrethrin-0.2.0.dist-info/licenses/LICENSE
pyrethrin-0.2.0.dist-info/RECORD
