Metadata-Version: 2.4
Name: pyrethrin
Version: 0.2.0
Summary: Rust-style exhaustive error and None handling for Python
Project-URL: Homepage, https://github.com/4tyone/pyrethrin
Project-URL: Repository, https://github.com/4tyone/pyrethrin
Project-URL: Documentation, https://github.com/4tyone/pyrethrin#readme
Author-email: Mel Shakobyan <mels@4tyone.com>
License-Expression: Apache-2.0
License-File: LICENSE
Keywords: error-handling,exceptions,exhaustive,pattern-matching,result
Classifier: Development Status :: 3 - Alpha
Classifier: Intended Audience :: Developers
Classifier: License :: OSI Approved :: Apache Software License
Classifier: Programming Language :: Python :: 3
Classifier: Programming Language :: Python :: 3.11
Classifier: Programming Language :: Python :: 3.12
Classifier: Programming Language :: Python :: 3.13
Classifier: Typing :: Typed
Requires-Python: >=3.11
Provides-Extra: dev
Requires-Dist: mypy>=1.8; extra == 'dev'
Requires-Dist: pytest-asyncio>=0.23; extra == 'dev'
Requires-Dist: pytest>=8.0; extra == 'dev'
Requires-Dist: ruff>=0.1; extra == 'dev'
Provides-Extra: static
